{
    "providers": [
        {
            "type": "bitmap",
            "file": "jakubprefix:prefix/root.png",
            "ascent": 7,
            "height": 8,
            "chars": ["ᜀ"]
        },
        {
            "type": "bitmap",
            "file": "jakubprefix:prefix/moderator.png",
            "ascent": 7,
            "height": 8,
            "chars": ["ᜁ"]
        },
        {
            "type": "bitmap",
            "file": "jakubprefix:prefix/vip.png",
            "ascent": 7,
            "height": 8,
            "chars": ["ᜂ"]
        },
        {
            "type": "bitmap",
            "file": "jakubprefix:prefix/gracz.png",
            "ascent": 7,
            "height": 8,
            "chars": ["ᜃ"]
        }
    ]
}
